sfs/__init__.py
sfs/array.py
sfs/plot2d.py
sfs/plot3d.py
sfs/tapering.py
sfs/util.py
sfs/fd/__init__.py
sfs/fd/esa.py
sfs/fd/nfchoa.py
sfs/fd/sdm.py
sfs/fd/source.py
sfs/fd/wfs.py
sfs/td/__init__.py
sfs/td/nfchoa.py
sfs/td/source.py
sfs/td/wfs.py
sfs-0.6.3.dist-info/licenses/LICENSE
sfs-0.6.3.dist-info/METADATA
sfs-0.6.3.dist-info/WHEEL
sfs-0.6.3.dist-info/top_level.txt
sfs-0.6.3.dist-info/RECORD
