Metadata-Version: 2.4
Name: sfs
Version: 0.6.3
Summary: Sound Field Synthesis Toolbox
Author-email: SFS Toolbox Developers <sfstoolbox@gmail.com>
License-Expression: MIT
Project-URL: Documentation, https://sfs-python.readthedocs.io/
Project-URL: Repository, https://github.com/sfstoolbox/sfs-python
Project-URL: Issues, https://github.com/sfstoolbox/sfs-python/issues
Keywords: audio,SFS,WFS,Ambisonics
Classifier: Operating System :: OS Independent
Classifier: Topic :: Scientific/Engineering
Requires-Python: >=3.11
License-File: LICENSE
Requires-Dist: numpy>=2
Requires-Dist: scipy>=1.16
Dynamic: license-file
